actrecipemagicfile-0.4.32.dist-info/RECORD
actrecipemagicfile-0.4.32.dist-info/METADATA
actrecipemagicfile-0.4.32.dist-info/WHEEL
actrecipemagicfile-0.4.32.dist-info/top_level.txt
actrecipemagicfile-0.4.32.dist-info/LICENSE
actrecipemagicfile.libs/libmagic-25687ccf.so.1.0.0
magicfile/_libmagic.abi3.so
magicfile/magic.mgc
magicfile/_libmagic_build.py
magicfile/__init__.py
