Metadata-Version: 2.1
Name: actrecipemagicfile
Version: 0.4.32
Summary: File type identification using libmagic
Home-page: https://github.com/tho-actrecipe/magicfile
Author: ActRecipe Inc.
Author-email: actrecipe-dev@actrecipe.com
License: MIT
Keywords: mime magic file
Platform: UNKNOWN
Classifier: Intended Audience :: Developers
Classifier: License :: OSI Approved :: MIT License
Classifier: Programming Language :: Python
Classifier: Programming Language :: Python :: 3.8
Classifier: Programming Language :: Python :: 3.9
Classifier: Programming Language :: Python :: 3.10
Classifier: Programming Language :: Python :: 3.11
Classifier: Programming Language :: Python :: 3.12
Classifier: Programming Language :: Python :: Implementation :: CPython
Requires-Python: >=3.8
License-File: LICENSE
Requires-Dist: cffi>=1.0.0
